PythonJingyaoJiaocheng/README.md
PythonJingyaoJiaocheng/__init__.py
PythonJingyaoJiaocheng/__main__.py
PythonJingyaoJiaocheng/file.epub
PythonJingyaoJiaocheng/index.html
PythonJingyaoJiaocheng/css/__init__.py
PythonJingyaoJiaocheng/css/annotations.css
PythonJingyaoJiaocheng/css/main.css
PythonJingyaoJiaocheng/css/normalize.css
PythonJingyaoJiaocheng/css/popup.css
PythonJingyaoJiaocheng/font/__init__.py
PythonJingyaoJiaocheng/font/fontello.eot
PythonJingyaoJiaocheng/font/fontello.svg
PythonJingyaoJiaocheng/font/fontello.ttf
PythonJingyaoJiaocheng/font/fontello.woff
PythonJingyaoJiaocheng/img/__init__.py
PythonJingyaoJiaocheng/img/annotator-glyph-sprite.png
PythonJingyaoJiaocheng/img/annotator-icon-sprite.png
PythonJingyaoJiaocheng/img/apple-touch-icon.png
PythonJingyaoJiaocheng/img/cancelfullscreen.png
PythonJingyaoJiaocheng/img/close.png
PythonJingyaoJiaocheng/img/fullscreen.png
PythonJingyaoJiaocheng/img/loader.gif
PythonJingyaoJiaocheng/img/menu-icon.png
PythonJingyaoJiaocheng/img/save.png
PythonJingyaoJiaocheng/img/saved.png
PythonJingyaoJiaocheng/img/settings-s.png
PythonJingyaoJiaocheng/img/settings.png
PythonJingyaoJiaocheng/img/star.png
PythonJingyaoJiaocheng/js/__init__.py
PythonJingyaoJiaocheng/js/epub.js
PythonJingyaoJiaocheng/js/epub.min.js
PythonJingyaoJiaocheng/js/epub.min.map
PythonJingyaoJiaocheng/js/hooks.min.js
PythonJingyaoJiaocheng/js/hooks.min.map
PythonJingyaoJiaocheng/js/reader.js
PythonJingyaoJiaocheng/js/reader.js.map
PythonJingyaoJiaocheng/js/reader.min.js
PythonJingyaoJiaocheng/js/reader.min.map
PythonJingyaoJiaocheng/js/hooks/__init__.py
PythonJingyaoJiaocheng/js/hooks/extensions/__init__.py
PythonJingyaoJiaocheng/js/hooks/extensions/highlight.js
PythonJingyaoJiaocheng/js/libs/__init__.py
PythonJingyaoJiaocheng/js/libs/jquery.min.js
PythonJingyaoJiaocheng/js/libs/localforage.min.js
PythonJingyaoJiaocheng/js/libs/screenfull.js
PythonJingyaoJiaocheng/js/libs/screenfull.min.js
PythonJingyaoJiaocheng/js/libs/zip.min.js
python_jingyao_jiaocheng-2024.3.1.0.dist-info/METADATA
python_jingyao_jiaocheng-2024.3.1.0.dist-info/WHEEL
python_jingyao_jiaocheng-2024.3.1.0.dist-info/entry_points.txt
python_jingyao_jiaocheng-2024.3.1.0.dist-info/top_level.txt
python_jingyao_jiaocheng-2024.3.1.0.dist-info/RECORD
